<?xml version="1.0" encoding="UTF-8"?>
<rl:ResultList xmlns:rl="http://meyton.org/2011/Schema/ResultList" xmlns:me="http://meyton.org/2011/Schema/MEXmlTypes" xmlns:xsi="http://www.w3.org/2001/XMLSchema-instance" xsi:schemaLocation="http://meyton.org/2011/Schema/ResultList file:/tftpboot/XML/Schema/Ergebnisliste.xsd" Version="0.2.1">
    <ResultRecord StartListID="70" StartID="5" LaneNo="4" RemainingTime="6645" TargetID="0b5d7804">
        <Shooter>
            <SportPassID>146</SportPassID>
            <FamilyName>Imgenberg</FamilyName>
            <GivenName>Horst</GivenName>
            <Gender>0</Gender>
        </Shooter>
        <MatchClass>
            <Name>offene Klasse</Name>
            <ID>99</ID>
        </MatchClass>
        <Club>
            <Name>SG Hamm III</Name>
            <ID>1</ID>
        </Club>
        <Team>
            <Name>SG Hamm III</Name>
            <ID>1</ID>
        </Team>
        <Discipline>
            <Name>LG Liga Auflage30</Name>
            <ID>10599030</ID>
        </Discipline>
        <Total>
            <Result>2950</Result>
            <Unit>Ring</Unit>
        </Total>
        <ShotNoTotal>30</ShotNoTotal>
        <Aimings>
            <AimingData AimingID="1">
                <AimingShotNo>30</AimingShotNo>
                <Series SeriesID="1">
                    <ValueSerie>
                        <Result>980</Result>
                        <Unit>Ring</Unit>
                    </ValueSerie>
                </Series>
                <Series SeriesID="2">
                    <ValueSerie>
                        <Result>1000</Result>
                        <Unit>Ring</Unit>
                    </ValueSerie>
                </Series>
                <Series SeriesID="3">
                    <ValueSerie>
                        <Result>970</Result>
                        <Unit>Ring</Unit>
                    </ValueSerie>
                </Series>
                <AimingTotal>
                    <Result>2950</Result>
                    <Unit>Ring</Unit>
                </AimingTotal>
                <Shot ShotID="1">
                    <Coordinate>
                        <CCoordinate Resolution="100">
                            <X>-237</X>
                            <Y>-13</Y>
                        </CCoordinate>
                    </Coordinate>
                    <RingValue>
                        <Result>100</Result>
                        <Unit>ZehntelRing</Unit>
                    </RingValue>
                    <RingValue>
                        <Result>237</Result>
                        <Unit>Teiler</Unit>
                    </RingValue>
                    <TimeStamp>
                        <DateTime>2015-09-23T19:13:32Z</DateTime>
                        <Hundredth>72</Hundredth>
                    </TimeStamp>
                </Shot>
                <Shot ShotID="2" IsInnerTen="true">
                    <Coordinate>
                        <CCoordinate Resolution="100">
                            <X>-34</X>
                            <Y>6</Y>
                        </CCoordinate>
                    </Coordinate>
                    <RingValue>
                        <Result>108</Result>
                        <Unit>ZehntelRing</Unit>
                    </RingValue>
                    <RingValue>
                        <Result>34</Result>
                        <Unit>Teiler</Unit>
                    </RingValue>
                    <TimeStamp>
                        <DateTime>2015-09-23T19:13:59Z</DateTime>
                        <Hundredth>52</Hundredth>
                    </TimeStamp>
                </Shot>
                <Shot ShotID="3" IsInnerTen="true">
                    <Coordinate>
                        <CCoordinate Resolution="100">
                            <X>71</X>
                            <Y>-19</Y>
                        </CCoordinate>
                    </Coordinate>
                    <RingValue>
                        <Result>107</Result>
                        <Unit>ZehntelRing</Unit>
                    </RingValue>
                    <RingValue>
                        <Result>73</Result>
                        <Unit>Teiler</Unit>
                    </RingValue>
                    <TimeStamp>
                        <DateTime>2015-09-23T19:14:31Z</DateTime>
                        <Hundredth>14</Hundredth>
                    </TimeStamp>
                </Shot>
                <Shot ShotID="4" IsInnerTen="true">
                    <Coordinate>
                        <CCoordinate Resolution="100">
                            <X>41</X>
                            <Y>-73</Y>
                        </CCoordinate>
                    </Coordinate>
                    <RingValue>
                        <Result>106</Result>
                        <Unit>ZehntelRing</Unit>
                    </RingValue>
                    <RingValue>
                        <Result>83</Result>
                        <Unit>Teiler</Unit>
                    </RingValue>
                    <TimeStamp>
                        <DateTime>2015-09-23T19:15:48Z</DateTime>
                        <Hundredth>65</Hundredth>
                    </TimeStamp>
                </Shot>
                <Shot ShotID="5" IsInnerTen="true">
                    <Coordinate>
                        <CCoordinate Resolution="100">
                            <X>26</X>
                            <Y>-47</Y>
                        </CCoordinate>
                    </Coordinate>
                    <RingValue>
                        <Result>107</Result>
                        <Unit>ZehntelRing</Unit>
                    </RingValue>
                    <RingValue>
                        <Result>53</Result>
                        <Unit>Teiler</Unit>
                    </RingValue>
                    <TimeStamp>
                        <DateTime>2015-09-23T19:16:29Z</DateTime>
                        <Hundredth>73</Hundredth>
                    </TimeStamp>
                </Shot>
                <Shot ShotID="6">
                    <Coordinate>
                        <CCoordinate Resolution="100">
                            <X>186</X>
                            <Y>-164</Y>
                        </CCoordinate>
                    </Coordinate>
                    <RingValue>
                        <Result>100</Result>
                        <Unit>ZehntelRing</Unit>
                    </RingValue>
                    <RingValue>
                        <Result>247</Result>
                        <Unit>Teiler</Unit>
                    </RingValue>
                    <TimeStamp>
                        <DateTime>2015-09-23T19:17:43Z</DateTime>
                        <Hundredth>19</Hundredth>
                    </TimeStamp>
                </Shot>
                <Shot ShotID="7">
                    <Coordinate>
                        <CCoordinate Resolution="100">
                            <X>276</X>
                            <Y>109</Y>
                        </CCoordinate>
                    </Coordinate>
                    <RingValue>
                        <Result>98</Result>
                        <Unit>ZehntelRing</Unit>
                    </RingValue>
                    <RingValue>
                        <Result>296</Result>
                        <Unit>Teiler</Unit>
                    </RingValue>
                    <TimeStamp>
                        <DateTime>2015-09-23T19:18:46Z</DateTime>
                        <Hundredth>42</Hundredth>
                    </TimeStamp>
                </Shot>
                <Shot ShotID="8">
                    <Coordinate>
                        <CCoordinate Resolution="100">
                            <X>-158</X>
                            <Y>-190</Y>
                        </CCoordinate>
                    </Coordinate>
                    <RingValue>
                        <Result>100</Result>
                        <Unit>ZehntelRing</Unit>
                    </RingValue>
                    <RingValue>
                        <Result>247</Result>
                        <Unit>Teiler</Unit>
                    </RingValue>
                    <TimeStamp>
                        <DateTime>2015-09-23T19:19:17Z</DateTime>
                        <Hundredth>0</Hundredth>
                    </TimeStamp>
                </Shot>
                <Shot ShotID="9">
                    <Coordinate>
                        <CCoordinate Resolution="100">
                            <X>-77</X>
                            <Y>-210</Y>
                        </CCoordinate>
                    </Coordinate>
                    <RingValue>
                        <Result>101</Result>
                        <Unit>ZehntelRing</Unit>
                    </RingValue>
                    <RingValue>
                        <Result>223</Result>
                        <Unit>Teiler</Unit>
                    </RingValue>
                    <TimeStamp>
                        <DateTime>2015-09-23T19:19:54Z</DateTime>
                        <Hundredth>42</Hundredth>
                    </TimeStamp>
                </Shot>
                <Shot ShotID="10">
                    <Coordinate>
                        <CCoordinate Resolution="100">
                            <X>244</X>
                            <Y>149</Y>
                        </CCoordinate>
                    </Coordinate>
                    <RingValue>
                        <Result>98</Result>
                        <Unit>ZehntelRing</Unit>
                    </RingValue>
                    <RingValue>
                        <Result>285</Result>
                        <Unit>Teiler</Unit>
                    </RingValue>
                    <TimeStamp>
                        <DateTime>2015-09-23T19:21:14Z</DateTime>
                        <Hundredth>11</Hundredth>
                    </TimeStamp>
                </Shot>
                <Shot ShotID="11">
                    <Coordinate>
                        <CCoordinate Resolution="100">
                            <X>218</X>
                            <Y>39</Y>
                        </CCoordinate>
                    </Coordinate>
                    <RingValue>
                        <Result>101</Result>
                        <Unit>ZehntelRing</Unit>
                    </RingValue>
                    <RingValue>
                        <Result>221</Result>
                        <Unit>Teiler</Unit>
                    </RingValue>
                    <TimeStamp>
                        <DateTime>2015-09-23T19:21:53Z</DateTime>
                        <Hundredth>43</Hundredth>
                    </TimeStamp>
                </Shot>
                <Shot ShotID="12" IsInnerTen="true">
                    <Coordinate>
                        <CCoordinate Resolution="100">
                            <X>189</X>
                            <Y>-11</Y>
                        </CCoordinate>
                    </Coordinate>
                    <RingValue>
                        <Result>102</Result>
                        <Unit>ZehntelRing</Unit>
                    </RingValue>
                    <RingValue>
                        <Result>189</Result>
                        <Unit>Teiler</Unit>
                    </RingValue>
                    <TimeStamp>
                        <DateTime>2015-09-23T19:22:29Z</DateTime>
                        <Hundredth>43</Hundredth>
                    </TimeStamp>
                </Shot>
                <Shot ShotID="13" IsInnerTen="true">
                    <Coordinate>
                        <CCoordinate Resolution="100">
                            <X>89</X>
                            <Y>15</Y>
                        </CCoordinate>
                    </Coordinate>
                    <RingValue>
                        <Result>106</Result>
                        <Unit>ZehntelRing</Unit>
                    </RingValue>
                    <RingValue>
                        <Result>90</Result>
                        <Unit>Teiler</Unit>
                    </RingValue>
                    <TimeStamp>
                        <DateTime>2015-09-23T19:23:45Z</DateTime>
                        <Hundredth>74</Hundredth>
                    </TimeStamp>
                </Shot>
                <Shot ShotID="14" IsInnerTen="true">
                    <Coordinate>
                        <CCoordinate Resolution="100">
                            <X>75</X>
                            <Y>99</Y>
                        </CCoordinate>
                    </Coordinate>
                    <RingValue>
                        <Result>105</Result>
                        <Unit>ZehntelRing</Unit>
                    </RingValue>
                    <RingValue>
                        <Result>124</Result>
                        <Unit>Teiler</Unit>
                    </RingValue>
                    <TimeStamp>
                        <DateTime>2015-09-23T19:24:24Z</DateTime>
                        <Hundredth>58</Hundredth>
                    </TimeStamp>
                </Shot>
                <Shot ShotID="15" IsInnerTen="true">
                    <Coordinate>
                        <CCoordinate Resolution="100">
                            <X>-69</X>
                            <Y>-54</Y>
                        </CCoordinate>
                    </Coordinate>
                    <RingValue>
                        <Result>106</Result>
                        <Unit>ZehntelRing</Unit>
                    </RingValue>
                    <RingValue>
                        <Result>87</Result>
                        <Unit>Teiler</Unit>
                    </RingValue>
                    <TimeStamp>
                        <DateTime>2015-09-23T19:25:06Z</DateTime>
                        <Hundredth>36</Hundredth>
                    </TimeStamp>
                </Shot>
                <Shot ShotID="16" IsInnerTen="true">
                    <Coordinate>
                        <CCoordinate Resolution="100">
                            <X>61</X>
                            <Y>-169</Y>
                        </CCoordinate>
                    </Coordinate>
                    <RingValue>
                        <Result>102</Result>
                        <Unit>ZehntelRing</Unit>
                    </RingValue>
                    <RingValue>
                        <Result>179</Result>
                        <Unit>Teiler</Unit>
                    </RingValue>
                    <TimeStamp>
                        <DateTime>2015-09-23T19:26:44Z</DateTime>
                        <Hundredth>15</Hundredth>
                    </TimeStamp>
                </Shot>
                <Shot ShotID="17" IsInnerTen="true">
                    <Coordinate>
                        <CCoordinate Resolution="100">
                            <X>50</X>
                            <Y>-139</Y>
                        </CCoordinate>
                    </Coordinate>
                    <RingValue>
                        <Result>104</Result>
                        <Unit>ZehntelRing</Unit>
                    </RingValue>
                    <RingValue>
                        <Result>147</Result>
                        <Unit>Teiler</Unit>
                    </RingValue>
                    <TimeStamp>
                        <DateTime>2015-09-23T19:29:02Z</DateTime>
                        <Hundredth>74</Hundredth>
                    </TimeStamp>
                </Shot>
                <Shot ShotID="18" IsInnerTen="true">
                    <Coordinate>
                        <CCoordinate Resolution="100">
                            <X>128</X>
                            <Y>22</Y>
                        </CCoordinate>
                    </Coordinate>
                    <RingValue>
                        <Result>104</Result>
                        <Unit>ZehntelRing</Unit>
                    </RingValue>
                    <RingValue>
                        <Result>129</Result>
                        <Unit>Teiler</Unit>
                    </RingValue>
                    <TimeStamp>
                        <DateTime>2015-09-23T19:29:44Z</DateTime>
                        <Hundredth>78</Hundredth>
                    </TimeStamp>
                </Shot>
                <Shot ShotID="19">
                    <Coordinate>
                        <CCoordinate Resolution="100">
                            <X>187</X>
                            <Y>-75</Y>
                        </CCoordinate>
                    </Coordinate>
                    <RingValue>
                        <Result>101</Result>
                        <Unit>ZehntelRing</Unit>
                    </RingValue>
                    <RingValue>
                        <Result>201</Result>
                        <Unit>Teiler</Unit>
                    </RingValue>
                    <TimeStamp>
                        <DateTime>2015-09-23T19:30:38Z</DateTime>
                        <Hundredth>49</Hundredth>
                    </TimeStamp>
                </Shot>
                <Shot ShotID="20" IsInnerTen="true">
                    <Coordinate>
                        <CCoordinate Resolution="100">
                            <X>160</X>
                            <Y>-16</Y>
                        </CCoordinate>
                    </Coordinate>
                    <RingValue>
                        <Result>103</Result>
                        <Unit>ZehntelRing</Unit>
                    </RingValue>
                    <RingValue>
                        <Result>160</Result>
                        <Unit>Teiler</Unit>
                    </RingValue>
                    <TimeStamp>
                        <DateTime>2015-09-23T19:32:32Z</DateTime>
                        <Hundredth>18</Hundredth>
                    </TimeStamp>
                </Shot>
                <Shot ShotID="21" IsInnerTen="true">
                    <Coordinate>
                        <CCoordinate Resolution="100">
                            <X>8</X>
                            <Y>-31</Y>
                        </CCoordinate>
                    </Coordinate>
                    <RingValue>
                        <Result>108</Result>
                        <Unit>ZehntelRing</Unit>
                    </RingValue>
                    <RingValue>
                        <Result>32</Result>
                        <Unit>Teiler</Unit>
                    </RingValue>
                    <TimeStamp>
                        <DateTime>2015-09-23T19:33:34Z</DateTime>
                        <Hundredth>73</Hundredth>
                    </TimeStamp>
                </Shot>
                <Shot ShotID="22" IsInnerTen="true">
                    <Coordinate>
                        <CCoordinate Resolution="100">
                            <X>-90</X>
                            <Y>51</Y>
                        </CCoordinate>
                    </Coordinate>
                    <RingValue>
                        <Result>105</Result>
                        <Unit>ZehntelRing</Unit>
                    </RingValue>
                    <RingValue>
                        <Result>103</Result>
                        <Unit>Teiler</Unit>
                    </RingValue>
                    <TimeStamp>
                        <DateTime>2015-09-23T19:35:17Z</DateTime>
                        <Hundredth>9</Hundredth>
                    </TimeStamp>
                </Shot>
                <Shot ShotID="23" IsInnerTen="true">
                    <Coordinate>
                        <CCoordinate Resolution="100">
                            <X>84</X>
                            <Y>26</Y>
                        </CCoordinate>
                    </Coordinate>
                    <RingValue>
                        <Result>106</Result>
                        <Unit>ZehntelRing</Unit>
                    </RingValue>
                    <RingValue>
                        <Result>87</Result>
                        <Unit>Teiler</Unit>
                    </RingValue>
                    <TimeStamp>
                        <DateTime>2015-09-23T19:36:04Z</DateTime>
                        <Hundredth>8</Hundredth>
                    </TimeStamp>
                </Shot>
                <Shot ShotID="24" IsInnerTen="true">
                    <Coordinate>
                        <CCoordinate Resolution="100">
                            <X>-162</X>
                            <Y>53</Y>
                        </CCoordinate>
                    </Coordinate>
                    <RingValue>
                        <Result>103</Result>
                        <Unit>ZehntelRing</Unit>
                    </RingValue>
                    <RingValue>
                        <Result>170</Result>
                        <Unit>Teiler</Unit>
                    </RingValue>
                    <TimeStamp>
                        <DateTime>2015-09-23T19:36:44Z</DateTime>
                        <Hundredth>22</Hundredth>
                    </TimeStamp>
                </Shot>
                <Shot ShotID="25">
                    <Coordinate>
                        <CCoordinate Resolution="100">
                            <X>235</X>
                            <Y>99</Y>
                        </CCoordinate>
                    </Coordinate>
                    <RingValue>
                        <Result>99</Result>
                        <Unit>ZehntelRing</Unit>
                    </RingValue>
                    <RingValue>
                        <Result>255</Result>
                        <Unit>Teiler</Unit>
                    </RingValue>
                    <TimeStamp>
                        <DateTime>2015-09-23T19:38:06Z</DateTime>
                        <Hundredth>63</Hundredth>
                    </TimeStamp>
                </Shot>
                <Shot ShotID="26" IsInnerTen="true">
                    <Coordinate>
                        <CCoordinate Resolution="100">
                            <X>-144</X>
                            <Y>26</Y>
                        </CCoordinate>
                    </Coordinate>
                    <RingValue>
                        <Result>104</Result>
                        <Unit>ZehntelRing</Unit>
                    </RingValue>
                    <RingValue>
                        <Result>146</Result>
                        <Unit>Teiler</Unit>
                    </RingValue>
                    <TimeStamp>
                        <DateTime>2015-09-23T19:38:54Z</DateTime>
                        <Hundredth>21</Hundredth>
                    </TimeStamp>
                </Shot>
                <Shot ShotID="27">
                    <Coordinate>
                        <CCoordinate Resolution="100">
                            <X>221</X>
                            <Y>220</Y>
                        </CCoordinate>
                    </Coordinate>
                    <RingValue>
                        <Result>97</Result>
                        <Unit>ZehntelRing</Unit>
                    </RingValue>
                    <RingValue>
                        <Result>311</Result>
                        <Unit>Teiler</Unit>
                    </RingValue>
                    <TimeStamp>
                        <DateTime>2015-09-23T19:39:29Z</DateTime>
                        <Hundredth>23</Hundredth>
                    </TimeStamp>
                </Shot>
                <Shot ShotID="28" IsInnerTen="true">
                    <Coordinate>
                        <CCoordinate Resolution="100">
                            <X>60</X>
                            <Y>30</Y>
                        </CCoordinate>
                    </Coordinate>
                    <RingValue>
                        <Result>107</Result>
                        <Unit>ZehntelRing</Unit>
                    </RingValue>
                    <RingValue>
                        <Result>67</Result>
                        <Unit>Teiler</Unit>
                    </RingValue>
                    <TimeStamp>
                        <DateTime>2015-09-23T19:40:43Z</DateTime>
                        <Hundredth>75</Hundredth>
                    </TimeStamp>
                </Shot>
                <Shot ShotID="29" IsInnerTen="true">
                    <Coordinate>
                        <CCoordinate Resolution="100">
                            <X>-92</X>
                            <Y>-59</Y>
                        </CCoordinate>
                    </Coordinate>
                    <RingValue>
                        <Result>105</Result>
                        <Unit>ZehntelRing</Unit>
                    </RingValue>
                    <RingValue>
                        <Result>109</Result>
                        <Unit>Teiler</Unit>
                    </RingValue>
                    <TimeStamp>
                        <DateTime>2015-09-23T19:41:17Z</DateTime>
                        <Hundredth>21</Hundredth>
                    </TimeStamp>
                </Shot>
                <Shot ShotID="30">
                    <Coordinate>
                        <CCoordinate Resolution="100">
                            <X>-251</X>
                            <Y>-25</Y>
                        </CCoordinate>
                    </Coordinate>
                    <RingValue>
                        <Result>99</Result>
                        <Unit>ZehntelRing</Unit>
                    </RingValue>
                    <RingValue>
                        <Result>252</Result>
                        <Unit>Teiler</Unit>
                    </RingValue>
                    <TimeStamp>
                        <DateTime>2015-09-23T19:41:55Z</DateTime>
                        <Hundredth>97</Hundredth>
                    </TimeStamp>
                </Shot>
            </AimingData>
        </Aimings>
    </ResultRecord>
</rl:ResultList>
