<?xml version="1.0" encoding="UTF-8"?>
<rl:ResultList xmlns:rl="http://meyton.org/2011/Schema/ResultList" xmlns:me="http://meyton.org/2011/Schema/MEXmlTypes" xmlns:xsi="http://www.w3.org/2001/XMLSchema-instance" xsi:schemaLocation="http://meyton.org/2011/Schema/ResultList file:/tftpboot/XML/Schema/Ergebnisliste.xsd" Version="0.2.1">
    <ResultRecord StartListID="22" StartID="431" LaneNo="6" RemainingTime="16577" TargetID="cd9cdc06">
        <Shooter>
            <SportPassID>288</SportPassID>
            <FamilyName>Schäper</FamilyName>
            <GivenName>Theo</GivenName>
            <Gender>0</Gender>
        </Shooter>
        <MatchClass>
            <Name>offene Klasse</Name>
            <ID>99</ID>
        </MatchClass>
        <Discipline>
            <Name>LG Auflage 30</Name>
            <ID>10111030</ID>
        </Discipline>
        <Total>
            <Result>2910</Result>
            <Unit>Ring</Unit>
        </Total>
        <ShotNoTotal>30</ShotNoTotal>
        <Aimings>
            <AimingData AimingID="1">
                <AimingShotNo>30</AimingShotNo>
                <Series SeriesID="1">
                    <ValueSerie>
                        <Result>1000</Result>
                        <Unit>Ring</Unit>
                    </ValueSerie>
                </Series>
                <Series SeriesID="2">
                    <ValueSerie>
                        <Result>950</Result>
                        <Unit>Ring</Unit>
                    </ValueSerie>
                </Series>
                <Series SeriesID="3">
                    <ValueSerie>
                        <Result>960</Result>
                        <Unit>Ring</Unit>
                    </ValueSerie>
                </Series>
                <AimingTotal>
                    <Result>2910</Result>
                    <Unit>Ring</Unit>
                </AimingTotal>
                <Shot ShotID="1" IsInnerTen="true">
                    <Coordinate>
                        <CCoordinate Resolution="100">
                            <X>37</X>
                            <Y>-179</Y>
                        </CCoordinate>
                    </Coordinate>
                    <RingValue>
                        <Result>102</Result>
                        <Unit>ZehntelRing</Unit>
                    </RingValue>
                    <RingValue>
                        <Result>182</Result>
                        <Unit>Teiler</Unit>
                    </RingValue>
                    <TimeStamp>
                        <DateTime>2015-07-25T12:54:31Z</DateTime>
                        <Hundredth>20</Hundredth>
                    </TimeStamp>
                </Shot>
                <Shot ShotID="2" IsInnerTen="true">
                    <Coordinate>
                        <CCoordinate Resolution="100">
                            <X>82</X>
                            <Y>-39</Y>
                        </CCoordinate>
                    </Coordinate>
                    <RingValue>
                        <Result>106</Result>
                        <Unit>ZehntelRing</Unit>
                    </RingValue>
                    <RingValue>
                        <Result>90</Result>
                        <Unit>Teiler</Unit>
                    </RingValue>
                    <TimeStamp>
                        <DateTime>2015-07-25T12:54:54Z</DateTime>
                        <Hundredth>20</Hundredth>
                    </TimeStamp>
                </Shot>
                <Shot ShotID="3">
                    <Coordinate>
                        <CCoordinate Resolution="100">
                            <X>177</X>
                            <Y>-157</Y>
                        </CCoordinate>
                    </Coordinate>
                    <RingValue>
                        <Result>100</Result>
                        <Unit>ZehntelRing</Unit>
                    </RingValue>
                    <RingValue>
                        <Result>236</Result>
                        <Unit>Teiler</Unit>
                    </RingValue>
                    <TimeStamp>
                        <DateTime>2015-07-25T12:55:24Z</DateTime>
                        <Hundredth>19</Hundredth>
                    </TimeStamp>
                </Shot>
                <Shot ShotID="4" IsInnerTen="true">
                    <Coordinate>
                        <CCoordinate Resolution="100">
                            <X>-150</X>
                            <Y>3</Y>
                        </CCoordinate>
                    </Coordinate>
                    <RingValue>
                        <Result>104</Result>
                        <Unit>ZehntelRing</Unit>
                    </RingValue>
                    <RingValue>
                        <Result>150</Result>
                        <Unit>Teiler</Unit>
                    </RingValue>
                    <TimeStamp>
                        <DateTime>2015-07-25T12:55:48Z</DateTime>
                        <Hundredth>78</Hundredth>
                    </TimeStamp>
                </Shot>
                <Shot ShotID="5" IsInnerTen="true">
                    <Coordinate>
                        <CCoordinate Resolution="100">
                            <X>-60</X>
                            <Y>73</Y>
                        </CCoordinate>
                    </Coordinate>
                    <RingValue>
                        <Result>106</Result>
                        <Unit>ZehntelRing</Unit>
                    </RingValue>
                    <RingValue>
                        <Result>94</Result>
                        <Unit>Teiler</Unit>
                    </RingValue>
                    <TimeStamp>
                        <DateTime>2015-07-25T12:56:20Z</DateTime>
                        <Hundredth>2</Hundredth>
                    </TimeStamp>
                </Shot>
                <Shot ShotID="6">
                    <Coordinate>
                        <CCoordinate Resolution="100">
                            <X>-200</X>
                            <Y>-68</Y>
                        </CCoordinate>
                    </Coordinate>
                    <RingValue>
                        <Result>101</Result>
                        <Unit>ZehntelRing</Unit>
                    </RingValue>
                    <RingValue>
                        <Result>211</Result>
                        <Unit>Teiler</Unit>
                    </RingValue>
                    <TimeStamp>
                        <DateTime>2015-07-25T12:56:48Z</DateTime>
                        <Hundredth>99</Hundredth>
                    </TimeStamp>
                </Shot>
                <Shot ShotID="7">
                    <Coordinate>
                        <CCoordinate Resolution="100">
                            <X>229</X>
                            <Y>-101</Y>
                        </CCoordinate>
                    </Coordinate>
                    <RingValue>
                        <Result>100</Result>
                        <Unit>ZehntelRing</Unit>
                    </RingValue>
                    <RingValue>
                        <Result>250</Result>
                        <Unit>Teiler</Unit>
                    </RingValue>
                    <TimeStamp>
                        <DateTime>2015-07-25T12:57:31Z</DateTime>
                        <Hundredth>37</Hundredth>
                    </TimeStamp>
                </Shot>
                <Shot ShotID="8" IsInnerTen="true">
                    <Coordinate>
                        <CCoordinate Resolution="100">
                            <X>10</X>
                            <Y>-33</Y>
                        </CCoordinate>
                    </Coordinate>
                    <RingValue>
                        <Result>108</Result>
                        <Unit>ZehntelRing</Unit>
                    </RingValue>
                    <RingValue>
                        <Result>34</Result>
                        <Unit>Teiler</Unit>
                    </RingValue>
                    <TimeStamp>
                        <DateTime>2015-07-25T12:57:56Z</DateTime>
                        <Hundredth>71</Hundredth>
                    </TimeStamp>
                </Shot>
                <Shot ShotID="9" IsInnerTen="true">
                    <Coordinate>
                        <CCoordinate Resolution="100">
                            <X>75</X>
                            <Y>-85</Y>
                        </CCoordinate>
                    </Coordinate>
                    <RingValue>
                        <Result>105</Result>
                        <Unit>ZehntelRing</Unit>
                    </RingValue>
                    <RingValue>
                        <Result>113</Result>
                        <Unit>Teiler</Unit>
                    </RingValue>
                    <TimeStamp>
                        <DateTime>2015-07-25T12:58:14Z</DateTime>
                        <Hundredth>16</Hundredth>
                    </TimeStamp>
                </Shot>
                <Shot ShotID="10" IsInnerTen="true">
                    <Coordinate>
                        <CCoordinate Resolution="100">
                            <X>-173</X>
                            <Y>36</Y>
                        </CCoordinate>
                    </Coordinate>
                    <RingValue>
                        <Result>102</Result>
                        <Unit>ZehntelRing</Unit>
                    </RingValue>
                    <RingValue>
                        <Result>176</Result>
                        <Unit>Teiler</Unit>
                    </RingValue>
                    <TimeStamp>
                        <DateTime>2015-07-25T12:58:36Z</DateTime>
                        <Hundredth>12</Hundredth>
                    </TimeStamp>
                </Shot>
                <Shot ShotID="11">
                    <Coordinate>
                        <CCoordinate Resolution="100">
                            <X>-281</X>
                            <Y>-26</Y>
                        </CCoordinate>
                    </Coordinate>
                    <RingValue>
                        <Result>98</Result>
                        <Unit>ZehntelRing</Unit>
                    </RingValue>
                    <RingValue>
                        <Result>282</Result>
                        <Unit>Teiler</Unit>
                    </RingValue>
                    <TimeStamp>
                        <DateTime>2015-07-25T12:59:38Z</DateTime>
                        <Hundredth>82</Hundredth>
                    </TimeStamp>
                </Shot>
                <Shot ShotID="12">
                    <Coordinate>
                        <CCoordinate Resolution="100">
                            <X>-293</X>
                            <Y>35</Y>
                        </CCoordinate>
                    </Coordinate>
                    <RingValue>
                        <Result>98</Result>
                        <Unit>ZehntelRing</Unit>
                    </RingValue>
                    <RingValue>
                        <Result>295</Result>
                        <Unit>Teiler</Unit>
                    </RingValue>
                    <TimeStamp>
                        <DateTime>2015-07-25T13:00:00Z</DateTime>
                        <Hundredth>93</Hundredth>
                    </TimeStamp>
                </Shot>
                <Shot ShotID="13" IsInnerTen="true">
                    <Coordinate>
                        <CCoordinate Resolution="100">
                            <X>43</X>
                            <Y>-34</Y>
                        </CCoordinate>
                    </Coordinate>
                    <RingValue>
                        <Result>107</Result>
                        <Unit>ZehntelRing</Unit>
                    </RingValue>
                    <RingValue>
                        <Result>54</Result>
                        <Unit>Teiler</Unit>
                    </RingValue>
                    <TimeStamp>
                        <DateTime>2015-07-25T13:00:25Z</DateTime>
                        <Hundredth>49</Hundredth>
                    </TimeStamp>
                </Shot>
                <Shot ShotID="14" IsInnerTen="true">
                    <Coordinate>
                        <CCoordinate Resolution="100">
                            <X>-15</X>
                            <Y>-125</Y>
                        </CCoordinate>
                    </Coordinate>
                    <RingValue>
                        <Result>105</Result>
                        <Unit>ZehntelRing</Unit>
                    </RingValue>
                    <RingValue>
                        <Result>125</Result>
                        <Unit>Teiler</Unit>
                    </RingValue>
                    <TimeStamp>
                        <DateTime>2015-07-25T13:00:47Z</DateTime>
                        <Hundredth>1</Hundredth>
                    </TimeStamp>
                </Shot>
                <Shot ShotID="15" IsInnerTen="true">
                    <Coordinate>
                        <CCoordinate Resolution="100">
                            <X>-53</X>
                            <Y>100</Y>
                        </CCoordinate>
                    </Coordinate>
                    <RingValue>
                        <Result>105</Result>
                        <Unit>ZehntelRing</Unit>
                    </RingValue>
                    <RingValue>
                        <Result>113</Result>
                        <Unit>Teiler</Unit>
                    </RingValue>
                    <TimeStamp>
                        <DateTime>2015-07-25T13:01:14Z</DateTime>
                        <Hundredth>97</Hundredth>
                    </TimeStamp>
                </Shot>
                <Shot ShotID="16" IsInnerTen="true">
                    <Coordinate>
                        <CCoordinate Resolution="100">
                            <X>181</X>
                            <Y>43</Y>
                        </CCoordinate>
                    </Coordinate>
                    <RingValue>
                        <Result>102</Result>
                        <Unit>ZehntelRing</Unit>
                    </RingValue>
                    <RingValue>
                        <Result>186</Result>
                        <Unit>Teiler</Unit>
                    </RingValue>
                    <TimeStamp>
                        <DateTime>2015-07-25T13:01:44Z</DateTime>
                        <Hundredth>23</Hundredth>
                    </TimeStamp>
                </Shot>
                <Shot ShotID="17">
                    <Coordinate>
                        <CCoordinate Resolution="100">
                            <X>337</X>
                            <Y>-65</Y>
                        </CCoordinate>
                    </Coordinate>
                    <RingValue>
                        <Result>96</Result>
                        <Unit>ZehntelRing</Unit>
                    </RingValue>
                    <RingValue>
                        <Result>343</Result>
                        <Unit>Teiler</Unit>
                    </RingValue>
                    <TimeStamp>
                        <DateTime>2015-07-25T13:02:12Z</DateTime>
                        <Hundredth>25</Hundredth>
                    </TimeStamp>
                </Shot>
                <Shot ShotID="18">
                    <Coordinate>
                        <CCoordinate Resolution="100">
                            <X>-201</X>
                            <Y>305</Y>
                        </CCoordinate>
                    </Coordinate>
                    <RingValue>
                        <Result>95</Result>
                        <Unit>ZehntelRing</Unit>
                    </RingValue>
                    <RingValue>
                        <Result>365</Result>
                        <Unit>Teiler</Unit>
                    </RingValue>
                    <TimeStamp>
                        <DateTime>2015-07-25T13:02:52Z</DateTime>
                        <Hundredth>80</Hundredth>
                    </TimeStamp>
                </Shot>
                <Shot ShotID="19" IsInnerTen="true">
                    <Coordinate>
                        <CCoordinate Resolution="100">
                            <X>-8</X>
                            <Y>121</Y>
                        </CCoordinate>
                    </Coordinate>
                    <RingValue>
                        <Result>105</Result>
                        <Unit>ZehntelRing</Unit>
                    </RingValue>
                    <RingValue>
                        <Result>121</Result>
                        <Unit>Teiler</Unit>
                    </RingValue>
                    <TimeStamp>
                        <DateTime>2015-07-25T13:03:11Z</DateTime>
                        <Hundredth>14</Hundredth>
                    </TimeStamp>
                </Shot>
                <Shot ShotID="20">
                    <Coordinate>
                        <CCoordinate Resolution="100">
                            <X>-455</X>
                            <Y>69</Y>
                        </CCoordinate>
                    </Coordinate>
                    <RingValue>
                        <Result>91</Result>
                        <Unit>ZehntelRing</Unit>
                    </RingValue>
                    <RingValue>
                        <Result>460</Result>
                        <Unit>Teiler</Unit>
                    </RingValue>
                    <TimeStamp>
                        <DateTime>2015-07-25T13:03:35Z</DateTime>
                        <Hundredth>0</Hundredth>
                    </TimeStamp>
                </Shot>
                <Shot ShotID="21" IsInnerTen="true">
                    <Coordinate>
                        <CCoordinate Resolution="100">
                            <X>-1</X>
                            <Y>-3</Y>
                        </CCoordinate>
                    </Coordinate>
                    <RingValue>
                        <Result>109</Result>
                        <Unit>ZehntelRing</Unit>
                    </RingValue>
                    <RingValue>
                        <Result>3</Result>
                        <Unit>Teiler</Unit>
                    </RingValue>
                    <TimeStamp>
                        <DateTime>2015-07-25T13:03:55Z</DateTime>
                        <Hundredth>80</Hundredth>
                    </TimeStamp>
                </Shot>
                <Shot ShotID="22">
                    <Coordinate>
                        <CCoordinate Resolution="100">
                            <X>177</X>
                            <Y>-278</Y>
                        </CCoordinate>
                    </Coordinate>
                    <RingValue>
                        <Result>96</Result>
                        <Unit>ZehntelRing</Unit>
                    </RingValue>
                    <RingValue>
                        <Result>329</Result>
                        <Unit>Teiler</Unit>
                    </RingValue>
                    <TimeStamp>
                        <DateTime>2015-07-25T13:04:22Z</DateTime>
                        <Hundredth>8</Hundredth>
                    </TimeStamp>
                </Shot>
                <Shot ShotID="23">
                    <Coordinate>
                        <CCoordinate Resolution="100">
                            <X>-172</X>
                            <Y>188</Y>
                        </CCoordinate>
                    </Coordinate>
                    <RingValue>
                        <Result>99</Result>
                        <Unit>ZehntelRing</Unit>
                    </RingValue>
                    <RingValue>
                        <Result>254</Result>
                        <Unit>Teiler</Unit>
                    </RingValue>
                    <TimeStamp>
                        <DateTime>2015-07-25T13:04:44Z</DateTime>
                        <Hundredth>42</Hundredth>
                    </TimeStamp>
                </Shot>
                <Shot ShotID="24">
                    <Coordinate>
                        <CCoordinate Resolution="100">
                            <X>52</X>
                            <Y>-196</Y>
                        </CCoordinate>
                    </Coordinate>
                    <RingValue>
                        <Result>101</Result>
                        <Unit>ZehntelRing</Unit>
                    </RingValue>
                    <RingValue>
                        <Result>202</Result>
                        <Unit>Teiler</Unit>
                    </RingValue>
                    <TimeStamp>
                        <DateTime>2015-07-25T13:05:06Z</DateTime>
                        <Hundredth>63</Hundredth>
                    </TimeStamp>
                </Shot>
                <Shot ShotID="25" IsInnerTen="true">
                    <Coordinate>
                        <CCoordinate Resolution="100">
                            <X>-172</X>
                            <Y>-88</Y>
                        </CCoordinate>
                    </Coordinate>
                    <RingValue>
                        <Result>102</Result>
                        <Unit>ZehntelRing</Unit>
                    </RingValue>
                    <RingValue>
                        <Result>193</Result>
                        <Unit>Teiler</Unit>
                    </RingValue>
                    <TimeStamp>
                        <DateTime>2015-07-25T13:05:26Z</DateTime>
                        <Hundredth>67</Hundredth>
                    </TimeStamp>
                </Shot>
                <Shot ShotID="26" IsInnerTen="true">
                    <Coordinate>
                        <CCoordinate Resolution="100">
                            <X>-91</X>
                            <Y>-87</Y>
                        </CCoordinate>
                    </Coordinate>
                    <RingValue>
                        <Result>105</Result>
                        <Unit>ZehntelRing</Unit>
                    </RingValue>
                    <RingValue>
                        <Result>125</Result>
                        <Unit>Teiler</Unit>
                    </RingValue>
                    <TimeStamp>
                        <DateTime>2015-07-25T13:05:44Z</DateTime>
                        <Hundredth>11</Hundredth>
                    </TimeStamp>
                </Shot>
                <Shot ShotID="27">
                    <Coordinate>
                        <CCoordinate Resolution="100">
                            <X>-267</X>
                            <Y>10</Y>
                        </CCoordinate>
                    </Coordinate>
                    <RingValue>
                        <Result>99</Result>
                        <Unit>ZehntelRing</Unit>
                    </RingValue>
                    <RingValue>
                        <Result>267</Result>
                        <Unit>Teiler</Unit>
                    </RingValue>
                    <TimeStamp>
                        <DateTime>2015-07-25T13:06:03Z</DateTime>
                        <Hundredth>65</Hundredth>
                    </TimeStamp>
                </Shot>
                <Shot ShotID="28" IsInnerTen="true">
                    <Coordinate>
                        <CCoordinate Resolution="100">
                            <X>-65</X>
                            <Y>0</Y>
                        </CCoordinate>
                    </Coordinate>
                    <RingValue>
                        <Result>107</Result>
                        <Unit>ZehntelRing</Unit>
                    </RingValue>
                    <RingValue>
                        <Result>65</Result>
                        <Unit>Teiler</Unit>
                    </RingValue>
                    <TimeStamp>
                        <DateTime>2015-07-25T13:06:24Z</DateTime>
                        <Hundredth>77</Hundredth>
                    </TimeStamp>
                </Shot>
                <Shot ShotID="29">
                    <Coordinate>
                        <CCoordinate Resolution="100">
                            <X>-266</X>
                            <Y>-3</Y>
                        </CCoordinate>
                    </Coordinate>
                    <RingValue>
                        <Result>99</Result>
                        <Unit>ZehntelRing</Unit>
                    </RingValue>
                    <RingValue>
                        <Result>266</Result>
                        <Unit>Teiler</Unit>
                    </RingValue>
                    <TimeStamp>
                        <DateTime>2015-07-25T13:06:48Z</DateTime>
                        <Hundredth>3</Hundredth>
                    </TimeStamp>
                </Shot>
                <Shot ShotID="30" IsInnerTen="true">
                    <Coordinate>
                        <CCoordinate Resolution="100">
                            <X>-153</X>
                            <Y>0</Y>
                        </CCoordinate>
                    </Coordinate>
                    <RingValue>
                        <Result>103</Result>
                        <Unit>ZehntelRing</Unit>
                    </RingValue>
                    <RingValue>
                        <Result>153</Result>
                        <Unit>Teiler</Unit>
                    </RingValue>
                    <TimeStamp>
                        <DateTime>2015-07-25T13:07:10Z</DateTime>
                        <Hundredth>92</Hundredth>
                    </TimeStamp>
                </Shot>
            </AimingData>
        </Aimings>
    </ResultRecord>
</rl:ResultList>
